{
  "name": "kessel-boilerplate",
  "version": "3.0.0",
  "description": "Boilerplate 3.0 mit Clerk, SpacetimeDB-Core, Supabase App DB plus Storage und 1Password fuer Secrets",
  "repository": "https://github.com/phkoenig/kessel-boilerplate",
  "author": "Philip König",
  "license": "MIT",
  "features": [
    "4-Spalten App Shell (Navbar, Explorer, Main, Assist)",
    "Clerk fuer Identity, Audience und User-Lifecycle",
    "SpacetimeDB als Boilerplate-Core fuer Rollen, Navigation, Wiki und Chat",
    "Supabase fuer App-Datenbank und Storage",
    "1Password-basierter Secrets- und pull-env-Workflow",
    "Realtime AI-Chat und tenant-spezifisches Branding"
  ],
  "requirements": {
    "node": ">=24.0.0",
    "pnpm": ">=9.0.0"
  },
  "supabase": {
    "project": "ufqlocxqizmiaozkashi"
  }
}
